<annotation>
	<folder>rys</folder>
	<filename>1 (3456).jpg</filename>
	<path>/home/hyr/Desktop/human/rys/1 (3456).jpg</path>
	<source>
		<database>Unknown</database>
	</source>
	<size>
		<width>566</width>
		<height>720</height>
		<depth>3</depth>
	</size>
	<segmented>0</segmented>
	<object>
		<name>human</name>
		<pose>Unspecified</pose>
		<truncated>0</truncated>
		<difficult>0</difficult>
		<bndbox>
			<xmin>200</xmin>
			<ymin>212</ymin>
			<xmax>385</xmax>
			<ymax>385</ymax>
		</bndbox>
	</object>
</annotation>
